test/__init__.py
test/all.py
test/audio.py
test/compiler.py
test/evaluator.py
test/example.py
test/example2.py
test/f_and_f.py
test/f_and_f2.py
test/first_follow.py
test/images.py
test/lang.py
test/main.py
test/new_one.py
test/solution.py
test/test.py
test/test2.py
test/video.py
test/x.py
test/xy.py
sql_compiler-0.1.6.dist-info/METADATA
sql_compiler-0.1.6.dist-info/WHEEL
sql_compiler-0.1.6.dist-info/top_level.txt
sql_compiler-0.1.6.dist-info/RECORD
